pkdb_analysis/__init__.py
pkdb_analysis/circos.py
pkdb_analysis/console.py
pkdb_analysis/core.py
pkdb_analysis/data.py
pkdb_analysis/dtypes.py
pkdb_analysis/envs.py
pkdb_analysis/filter.py
pkdb_analysis/kernels.py
pkdb_analysis/log.py
pkdb_analysis/logging_utils.py
pkdb_analysis/query.py
pkdb_analysis/units.py
pkdb_analysis/utils.py
pkdb_analysis/utils_caffeine.py
pkdb_analysis/inference/__init__.py
pkdb_analysis/inference/body_weight.py
pkdb_analysis/pk/__init__.py
pkdb_analysis/pk/pharmacokinetics.py
pkdb_analysis/pk/pharmacokinetics_example.py
pkdb_analysis/plotting/__init__.py
pkdb_analysis/plotting/factory.py
pkdb_analysis/plotting/plotting.py
pkdb_analysis/reports/__init__.py
pkdb_analysis/reports/effect_analysis.py
pkdb_analysis/reports/latex.py
pkdb_analysis/reports/tables.py
pkdb_analysis/reports/interactive/__init__.py
pkdb_analysis/reports/interactive/interactive.py
pkdb_analysis/reports/interactive/examples/__init__.py
pkdb_analysis/reports/interactive/examples/example1.py
pkdb_analysis/reports/interactive/template/.gitignore
pkdb_analysis/reports/interactive/template/404.html
pkdb_analysis/reports/interactive/template/Gemfile
pkdb_analysis/reports/interactive/template/Gemfile.lock
pkdb_analysis/reports/interactive/template/README.md
pkdb_analysis/reports/interactive/template/_config.yml
pkdb_analysis/reports/interactive/template/docker-compose-serve.yml
pkdb_analysis/reports/interactive/template/index.md
pkdb_analysis/reports/interactive/template/pk.md
pkdb_analysis/reports/interactive/template/_includes/head-scripts.html
pkdb_analysis/reports/interactive/template/_includes/head.html
pkdb_analysis/reports/interactive/template/_includes/header.html
pkdb_analysis/reports/interactive/template/_layouts/default.html
pkdb_analysis/reports/interactive/template/_layouts/page.html
pkdb_analysis/reports/interactive/template/_layouts/pk.html
pkdb_analysis/reports/interactive/template/assets/css/app.scss
pkdb_analysis/reports/interactive/template/assets/js/app.js
pkdb_analysis-0.3.1.dist-info/METADATA
pkdb_analysis-0.3.1.dist-info/WHEEL
pkdb_analysis-0.3.1.dist-info/licenses/LICENSE
pkdb_analysis-0.3.1.dist-info/RECORD
