Metadata-Version: 2.4
Name: pkdb-analysis
Version: 0.3.1
Summary: Python utilities for PK-DB.
Author-email: Matthias König <konigmatt@googlemail.com>
Maintainer-email: Matthias König <konigmatt@googlemail.com>
License-File: LICENSE
Keywords: PK-DB,pharmacokinetics,standardization
Classifier: Development Status :: 4 - Beta
Classifier: Intended Audience :: Science/Research
Classifier: License :: OSI Approved :: MIT License
Classifier: Operating System :: OS Independent
Classifier: Programming Language :: Python :: 3.11
Classifier: Programming Language :: Python :: 3.12
Classifier: Programming Language :: Python :: 3.13
Classifier: Programming Language :: Python :: Implementation :: CPython
Classifier: Topic :: Scientific/Engineering
Classifier: Topic :: Scientific/Engineering :: Bio-Informatics
Requires-Python: >=3.11
Requires-Dist: altair>=4.1.0
Requires-Dist: coloredlogs>=14.0
Requires-Dist: depinfo>=0.1.7
Requires-Dist: gspread-pandas>=2.2.3
Requires-Dist: ipython
Requires-Dist: matplotlib>=3.4
Requires-Dist: numpy>=2.2
Requires-Dist: openpyxl>=3.0.5
Requires-Dist: pandas>=1.3
Requires-Dist: pint>=0.17
Requires-Dist: pyyaml>=5.3.1
Requires-Dist: requests>=2.24.0
Requires-Dist: rich
Requires-Dist: scikit-learn>=0.24.2
Requires-Dist: seaborn>=0.11.1
Requires-Dist: xlsxwriter>=1.3.7
Provides-Extra: dev
Requires-Dist: bump-my-version>=1.2.4; extra == 'dev'
Requires-Dist: mypy>=1.18.2; extra == 'dev'
Requires-Dist: pre-commit>=4.3.0; extra == 'dev'
Requires-Dist: ruff>=0.14.0; extra == 'dev'
Provides-Extra: test
Requires-Dist: pytest-cov>=7.0.0; extra == 'test'
Requires-Dist: pytest>=8.4.2; extra == 'test'
Requires-Dist: tox>=4.31.0; extra == 'test'
